{"tracks": [{"name": "Paint The Town Red", "id": "7DlZH8EiVDgQXNoj3dnyZC", "audio_features": {"danceability": 0.864, "energy": 0.556, "key": 2, "loudness": -7.683, "mode": 0, "speechiness": 0.194, "acousticness": 0.255, "instrumentalness": 3.85e-06, "liveness": 0.112, "valence": 0.726, "tempo": 99.974, "type": "audio_features", "id": "7DlZH8EiVDgQXNoj3dnyZC", "uri": "spotify:track:7DlZH8EiVDgQXNoj3dnyZC", "track_href": "https://api.spotify.com/v1/tracks/7DlZH8EiVDgQXNoj3dnyZC", "analysis_url": "https://api.spotify.com/v1/audio-analysis/7DlZH8EiVDgQXNoj3dnyZC", "duration_ms": 230480, "time_signature": 4}}, {"name": "Demons", "id": "6vb4kCEIM7zrwuHlxFbfeB", "audio_features": {"danceability": 0.831, "energy": 0.362, "key": 1, "loudness": -6.085, "mode": 1, "speechiness": 0.229, "acousticness": 0.000156, "instrumentalness": 0.0162, "liveness": 0.168, "valence": 0.313, "tempo": 139.941, "type": "audio_features", "id": "6vb4kCEIM7zrwuHlxFbfeB", "uri": "spotify:track:6vb4kCEIM7zrwuHlxFbfeB", "track_href": "https://api.spotify.com/v1/tracks/6vb4kCEIM7zrwuHlxFbfeB", "analysis_url": "https://api.spotify.com/v1/audio-analysis/6vb4kCEIM7zrwuHlxFbfeB", "duration_ms": 195573, "time_signature": 4}}, {"name": "Wet Vagina", "id": "5MqauQV2PhcEFfhKtBOTua", "audio_features": {"danceability": 0.804, "energy": 0.656, "key": 6, "loudness": -5.723, "mode": 0, "speechiness": 0.0896, "acousticness": 0.0207, "instrumentalness": 1.86e-05, "liveness": 0.107, "valence": 0.192, "tempo": 150.014, "type": "audio_features", "id": "5MqauQV2PhcEFfhKtBOTua", "uri": "spotify:track:5MqauQV2PhcEFfhKtBOTua", "track_href": "https://api.spotify.com/v1/tracks/5MqauQV2PhcEFfhKtBOTua", "analysis_url": "https://api.spotify.com/v1/audio-analysis/5MqauQV2PhcEFfhKtBOTua", "duration_ms": 192240, "time_signature": 4}}, {"name": "Fuck The Girls (FTG)", "id": "6DOphQTeNmy1gk3um8sPYC", "audio_features": {"danceability": 0.764, "energy": 0.72, "key": 7, "loudness": -6.494, "mode": 1, "speechiness": 0.273, "acousticness": 0.196, "instrumentalness": 3.46e-05, "liveness": 0.111, "valence": 0.643, "tempo": 91.337, "type": "audio_features", "id": "6DOphQTeNmy1gk3um8sPYC", "uri": "spotify:track:6DOphQTeNmy1gk3um8sPYC", "track_href": "https://api.spotify.com/v1/tracks/6DOphQTeNmy1gk3um8sPYC", "analysis_url": "https://api.spotify.com/v1/audio-analysis/6DOphQTeNmy1gk3um8sPYC", "duration_ms": 152867, "time_signature": 4}}, {"name": "Ouchies", "id": "18EGw1StZNDftpUcX8PM74", "audio_features": {"danceability": 0.854, "energy": 0.808, "key": 1, "loudness": -5.958, "mode": 1, "speechiness": 0.139, "acousticness": 0.0194, "instrumentalness": 2.41e-06, "liveness": 0.108, "valence": 0.794, "tempo": 110.203, "type": "audio_features", "id": "18EGw1StZNDftpUcX8PM74", "uri": "spotify:track:18EGw1StZNDftpUcX8PM74", "track_href": "https://api.spotify.com/v1/tracks/18EGw1StZNDftpUcX8PM74", "analysis_url": "https://api.spotify.com/v1/audio-analysis/18EGw1StZNDftpUcX8PM74", "duration_ms": 122187, "time_signature": 4}}, {"name": "97", "id": "3zLwDjumhvIFFwAAZaDNPL", "audio_features": {"danceability": 0.564, "energy": 0.796, "key": 5, "loudness": -2.652, "mode": 0, "speechiness": 0.351, "acousticness": 0.184, "instrumentalness": 0, "liveness": 0.147, "valence": 0.864, "tempo": 153.586, "type": "audio_features", "id": "3zLwDjumhvIFFwAAZaDNPL", "uri": "spotify:track:3zLwDjumhvIFFwAAZaDNPL", "track_href": "https://api.spotify.com/v1/tracks/3zLwDjumhvIFFwAAZaDNPL", "analysis_url": "https://api.spotify.com/v1/audio-analysis/3zLwDjumhvIFFwAAZaDNPL", "duration_ms": 177667, "time_signature": 4}}, {"name": "Gun", "id": "15sNe8FD178zMsVz6ug0AS", "audio_features": {"danceability": 0.885, "energy": 0.576, "key": 10, "loudness": -7.17, "mode": 0, "speechiness": 0.238, "acousticness": 0.0695, "instrumentalness": 0.000235, "liveness": 0.0993, "valence": 0.805, "tempo": 76.004, "type": "audio_features", "id": "15sNe8FD178zMsVz6ug0AS", "uri": "spotify:track:15sNe8FD178zMsVz6ug0AS", "track_href": "https://api.spotify.com/v1/tracks/15sNe8FD178zMsVz6ug0AS", "analysis_url": "https://api.spotify.com/v1/audio-analysis/15sNe8FD178zMsVz6ug0AS", "duration_ms": 176840, "time_signature": 4}}, {"name": "Go Off", "id": "032UZ3KVrzII6AE9Abnj7z", "audio_features": {"danceability": 0.933, "energy": 0.533, "key": 5, "loudness": -8.0, "mode": 0, "speechiness": 0.0585, "acousticness": 0.027, "instrumentalness": 0.00416, "liveness": 0.118, "valence": 0.552, "tempo": 140.991, "type": "audio_features", "id": "032UZ3KVrzII6AE9Abnj7z", "uri": "spotify:track:032UZ3KVrzII6AE9Abnj7z", "track_href": "https://api.spotify.com/v1/tracks/032UZ3KVrzII6AE9Abnj7z", "analysis_url": "https://api.spotify.com/v1/audio-analysis/032UZ3KVrzII6AE9Abnj7z", "duration_ms": 197493, "time_signature": 4}}, {"name": "Shutcho", "id": "4rjQxlKAIXbEqHzjrnYZ7x", "audio_features": {"danceability": 0.763, "energy": 0.441, "key": 1, "loudness": -9.043, "mode": 1, "speechiness": 0.11, "acousticness": 0.0343, "instrumentalness": 0, "liveness": 0.132, "valence": 0.409, "tempo": 145.926, "type": "audio_features", "id": "4rjQxlKAIXbEqHzjrnYZ7x", "uri": "spotify:track:4rjQxlKAIXbEqHzjrnYZ7x", "track_href": "https://api.spotify.com/v1/tracks/4rjQxlKAIXbEqHzjrnYZ7x", "analysis_url": "https://api.spotify.com/v1/audio-analysis/4rjQxlKAIXbEqHzjrnYZ7x", "duration_ms": 187400, "time_signature": 4}}, {"name": "Agora Hills", "id": "7dJYggqjKo71KI9sLzqCs8", "audio_features": {"danceability": 0.75, "energy": 0.674, "key": 8, "loudness": -6.128, "mode": 0, "speechiness": 0.097, "acousticness": 0.228, "instrumentalness": 8.91e-05, "liveness": 0.122, "valence": 0.392, "tempo": 123.026, "type": "audio_features", "id": "7dJYggqjKo71KI9sLzqCs8", "uri": "spotify:track:7dJYggqjKo71KI9sLzqCs8", "track_href": "https://api.spotify.com/v1/tracks/7dJYggqjKo71KI9sLzqCs8", "analysis_url": "https://api.spotify.com/v1/audio-analysis/7dJYggqjKo71KI9sLzqCs8", "duration_ms": 265360, "time_signature": 4}}, {"name": "Can't Wait", "id": "5ZyQqAgrPr0cVm0VfM69Np", "audio_features": {"danceability": 0.472, "energy": 0.79, "key": 6, "loudness": -4.337, "mode": 0, "speechiness": 0.322, "acousticness": 0.286, "instrumentalness": 3.45e-06, "liveness": 0.0636, "valence": 0.815, "tempo": 77.908, "type": "audio_features", "id": "5ZyQqAgrPr0cVm0VfM69Np", "uri": "spotify:track:5ZyQqAgrPr0cVm0VfM69Np", "track_href": "https://api.spotify.com/v1/tracks/5ZyQqAgrPr0cVm0VfM69Np", "analysis_url": "https://api.spotify.com/v1/audio-analysis/5ZyQqAgrPr0cVm0VfM69Np", "duration_ms": 235360, "time_signature": 4}}, {"name": "Often", "id": "18dR6VljfkTb47HJOQ9chv", "audio_features": {"danceability": 0.509, "energy": 0.638, "key": 9, "loudness": -5.516, "mode": 1, "speechiness": 0.475, "acousticness": 0.554, "instrumentalness": 0.108, "liveness": 0.11, "valence": 0.593, "tempo": 171.817, "type": "audio_features", "id": "18dR6VljfkTb47HJOQ9chv", "uri": "spotify:track:18dR6VljfkTb47HJOQ9chv", "track_href": "https://api.spotify.com/v1/tracks/18dR6VljfkTb47HJOQ9chv", "analysis_url": "https://api.spotify.com/v1/audio-analysis/18dR6VljfkTb47HJOQ9chv", "duration_ms": 198107, "time_signature": 4}}, {"name": "Love Life", "id": "4NW3t9GA7CyBisyoROefUs", "audio_features": {"danceability": 0.597, "energy": 0.622, "key": 1, "loudness": -9.593, "mode": 1, "speechiness": 0.343, "acousticness": 0.616, "instrumentalness": 0.00299, "liveness": 0.121, "valence": 0.649, "tempo": 82.361, "type": "audio_features", "id": "4NW3t9GA7CyBisyoROefUs", "uri": "spotify:track:4NW3t9GA7CyBisyoROefUs", "track_href": "https://api.spotify.com/v1/tracks/4NW3t9GA7CyBisyoROefUs", "analysis_url": "https://api.spotify.com/v1/audio-analysis/4NW3t9GA7CyBisyoROefUs", "duration_ms": 236960, "time_signature": 4}}, {"name": "Skull And Bones", "id": "3qefkziLSTq2l5H1bRoea8", "audio_features": {"danceability": 0.632, "energy": 0.706, "key": 11, "loudness": -6.127, "mode": 0, "speechiness": 0.0987, "acousticness": 0.106, "instrumentalness": 5.09e-05, "liveness": 0.143, "valence": 0.501, "tempo": 85.0, "type": "audio_features", "id": "3qefkziLSTq2l5H1bRoea8", "uri": "spotify:track:3qefkziLSTq2l5H1bRoea8", "track_href": "https://api.spotify.com/v1/tracks/3qefkziLSTq2l5H1bRoea8", "analysis_url": "https://api.spotify.com/v1/audio-analysis/3qefkziLSTq2l5H1bRoea8", "duration_ms": 248440, "time_signature": 4}}, {"name": "Attention", "id": "56uOalQCSny79UjPrefkHy", "audio_features": {"danceability": 0.758, "energy": 0.587, "key": 2, "loudness": -6.932, "mode": 1, "speechiness": 0.244, "acousticness": 0.13, "instrumentalness": 0.0173, "liveness": 0.109, "valence": 0.395, "tempo": 87.997, "type": "audio_features", "id": "56uOalQCSny79UjPrefkHy", "uri": "spotify:track:56uOalQCSny79UjPrefkHy", "track_href": "https://api.spotify.com/v1/tracks/56uOalQCSny79UjPrefkHy", "analysis_url": "https://api.spotify.com/v1/audio-analysis/56uOalQCSny79UjPrefkHy", "duration_ms": 275507, "time_signature": 4}}, {"name": "Balut", "id": "3yeVb5di44wD6CZ2sJromR", "audio_features": {"danceability": 0.778, "energy": 0.626, "key": 0, "loudness": -4.329, "mode": 1, "speechiness": 0.161, "acousticness": 0.183, "instrumentalness": 0.127, "liveness": 0.177, "valence": 0.377, "tempo": 148.022, "type": "audio_features", "id": "3yeVb5di44wD6CZ2sJromR", "uri": "spotify:track:3yeVb5di44wD6CZ2sJromR", "track_href": "https://api.spotify.com/v1/tracks/3yeVb5di44wD6CZ2sJromR", "analysis_url": "https://api.spotify.com/v1/audio-analysis/3yeVb5di44wD6CZ2sJromR", "duration_ms": 205453, "time_signature": 4}}, {"name": "WYM Freestyle", "id": "1qimDZEBflJE25RXkF24Yg", "audio_features": {"danceability": 0.895, "energy": 0.486, "key": 1, "loudness": -5.937, "mode": 1, "speechiness": 0.273, "acousticness": 0.00449, "instrumentalness": 0.00733, "liveness": 0.119, "valence": 0.375, "tempo": 144.064, "type": "audio_features", "id": "1qimDZEBflJE25RXkF24Yg", "uri": "spotify:track:1qimDZEBflJE25RXkF24Yg", "track_href": "https://api.spotify.com/v1/tracks/1qimDZEBflJE25RXkF24Yg", "analysis_url": "https://api.spotify.com/v1/audio-analysis/1qimDZEBflJE25RXkF24Yg", "duration_ms": 124107, "time_signature": 4}}], "artist_info": {"popularity": 87, "followers": 27074075, "genres": ["dance pop", "pop"], "images": [{"height": 640, "url": "https://i.scdn.co/image/ab6761610000e5eb7f6d6cac38d494e87692af99", "width": 640}, {"height": 320, "url": "https://i.scdn.co/image/ab676161000051747f6d6cac38d494e87692af99", "width": 320}, {"height": 160, "url": "https://i.scdn.co/image/ab6761610000f1787f6d6cac38d494e87692af99", "width": 160}], "external_urls": {"spotify": "https://open.spotify.com/artist/5cj0lLjcoR7YOSnhnX0Po5"}, "spotify_uri": "spotify:artist:5cj0lLjcoR7YOSnhnX0Po5", "spotify_url": "https://open.spotify.com/artist/5cj0lLjcoR7YOSnhnX0Po5"}}