[{"artists": [{"external_urls": {"spotify": "https://open.spotify.com/artist/4kqFrZkeqDfOIEqTWqbOOV"}, "href": "https://api.spotify.com/v1/artists/4kqFrZkeqDfOIEqTWqbOOV", "id": "4kqFrZkeqDfOIEqTWqbOOV", "name": "brakence", "type": "artist", "uri": "spotify:artist:4kqFrZkeqDfOIEqTWqbOOV"}], "available_markets": ["AR", "AU", "AT", "BE", "BO", "BR", "BG", "CA", "CL", "CO", "CR", "CY", "CZ", "DK", "DO", "DE", "EC", "EE", "SV", "FI", "FR", "GR", "GT", "HN", "HK", "HU", "IS", "IE", "IT", "LV", "LT", "LU", "MY", "MT", "MX", "NL", "NZ", "NI", "NO", "PA", "PY", "PE", "PH", "PL", "PT", "SG", "SK", "ES", "SE", "CH", "TW", "TR", "UY", "US", "GB", "AD", "LI", "MC", "ID", "JP", "TH", "VN", "RO", "IL", "ZA", "SA", "AE", "BH", "QA", "OM", "KW", "EG", "MA", "DZ", "TN", "LB", "JO", "PS", "IN", "BY", "KZ", "MD", "UA", "AL", "BA", "HR", "ME", "MK", "RS", "SI", "KR", "BD", "PK", "LK", "GH", "KE", "NG", "TZ", "UG", "AG", "AM", "BS", "BB", "BZ", "BT", "BW", "BF", "CV", "CW", "DM", "FJ", "GM", "GE", "GD", "GW", "GY", "HT", "JM", "KI", "LS", "LR", "MW", "MV", "ML", "MH", "FM", "NA", "NR", "NE", "PW", "PG", "WS", "SM", "ST", "SN", "SC", "SL", "SB", "KN", "LC", "VC", "SR", "TL", "TO", "TT", "TV", "VU", "AZ", "BN", "BI", "KH", "CM", "TD", "KM", "GQ", "SZ", "GA", "GN", "KG", "LA", "MO", "MR", "MN", "NP", "RW", "TG", "UZ", "ZW", "BJ", "MG", "MU", "MZ", "AO", "CI", "DJ", "ZM", "CD", "CG", "IQ", "LY", "TJ", "VE", "ET", "XK"], "disc_number": 1, "duration_ms": 196693, "explicit": true, "external_urls": {"spotify": "https://open.spotify.com/track/68gdFKpX6VAddnn2UFgZVG"}, "href": "https://api.spotify.com/v1/tracks/68gdFKpX6VAddnn2UFgZVG", "id": "68gdFKpX6VAddnn2UFgZVG", "is_local": false, "name": "bugging!", "preview_url": "https://p.scdn.co/mp3-preview/b71cc54c8680ee25e811773f6332c4bb33a9b021?cid=2a85e163bc1d4deeb6569f6e2aff09cf", "track_number": 1, "type": "track", "uri": "spotify:track:68gdFKpX6VAddnn2UFgZVG"}, {"artists": [{"external_urls": {"spotify": "https://open.spotify.com/artist/4kqFrZkeqDfOIEqTWqbOOV"}, "href": "https://api.spotify.com/v1/artists/4kqFrZkeqDfOIEqTWqbOOV", "id": "4kqFrZkeqDfOIEqTWqbOOV", "name": "brakence", "type": "artist", "uri": "spotify:artist:4kqFrZkeqDfOIEqTWqbOOV"}], "available_markets": ["AR", "AU", "AT", "BE", "BO", "BR", "BG", "CA", "CL", "CO", "CR", "CY", "CZ", "DK", "DO", "DE", "EC", "EE", "SV", "FI", "FR", "GR", "GT", "HN", "HK", "HU", "IS", "IE", "IT", "LV", "LT", "LU", "MY", "MT", "MX", "NL", "NZ", "NI", "NO", "PA", "PY", "PE", "PH", "PL", "PT", "SG", "SK", "ES", "SE", "CH", "TW", "TR", "UY", "US", "GB", "AD", "LI", "MC", "ID", "JP", "TH", "VN", "RO", "IL", "ZA", "SA", "AE", "BH", "QA", "OM", "KW", "EG", "MA", "DZ", "TN", "LB", "JO", "PS", "IN", "BY", "KZ", "MD", "UA", "AL", "BA", "HR", "ME", "MK", "RS", "SI", "KR", "BD", "PK", "LK", "GH", "KE", "NG", "TZ", "UG", "AG", "AM", "BS", "BB", "BZ", "BT", "BW", "BF", "CV", "CW", "DM", "FJ", "GM", "GE", "GD", "GW", "GY", "HT", "JM", "KI", "LS", "LR", "MW", "MV", "ML", "MH", "FM", "NA", "NR", "NE", "PW", "PG", "WS", "SM", "ST", "SN", "SC", "SL", "SB", "KN", "LC", "VC", "SR", "TL", "TO", "TT", "TV", "VU", "AZ", "BN", "BI", "KH", "CM", "TD", "KM", "GQ", "SZ", "GA", "GN", "KG", "LA", "MO", "MR", "MN", "NP", "RW", "TG", "UZ", "ZW", "BJ", "MG", "MU", "MZ", "AO", "CI", "DJ", "ZM", "CD", "CG", "IQ", "LY", "TJ", "VE", "ET", "XK"], "disc_number": 1, "duration_ms": 197106, "explicit": true, "external_urls": {"spotify": "https://open.spotify.com/track/5oPOob0I5zgbXo3j6Trb2k"}, "href": "https://api.spotify.com/v1/tracks/5oPOob0I5zgbXo3j6Trb2k", "id": "5oPOob0I5zgbXo3j6Trb2k", "is_local": false, "name": "caffeine", "preview_url": "https://p.scdn.co/mp3-preview/743213222c99633cd9fefbd3cea6cb5a4dcd1358?cid=2a85e163bc1d4deeb6569f6e2aff09cf", "track_number": 2, "type": "track", "uri": "spotify:track:5oPOob0I5zgbXo3j6Trb2k"}, {"artists": [{"external_urls": {"spotify": "https://open.spotify.com/artist/4kqFrZkeqDfOIEqTWqbOOV"}, "href": "https://api.spotify.com/v1/artists/4kqFrZkeqDfOIEqTWqbOOV", "id": "4kqFrZkeqDfOIEqTWqbOOV", "name": "brakence", "type": "artist", "uri": "spotify:artist:4kqFrZkeqDfOIEqTWqbOOV"}], "available_markets": ["AR", "AU", "AT", "BE", "BO", "BR", "BG", "CA", "CL", "CO", "CR", "CY", "CZ", "DK", "DO", "DE", "EC", "EE", "SV", "FI", "FR", "GR", "GT", "HN", "HK", "HU", "IS", "IE", "IT", "LV", "LT", "LU", "MY", "MT", "MX", "NL", "NZ", "NI", "NO", "PA", "PY", "PE", "PH", "PL", "PT", "SG", "SK", "ES", "SE", "CH", "TW", "TR", "UY", "US", "GB", "AD", "LI", "MC", "ID", "JP", "TH", "VN", "RO", "IL", "ZA", "SA", "AE", "BH", "QA", "OM", "KW", "EG", "MA", "DZ", "TN", "LB", "JO", "PS", "IN", "BY", "KZ", "MD", "UA", "AL", "BA", "HR", "ME", "MK", "RS", "SI", "KR", "BD", "PK", "LK", "GH", "KE", "NG", "TZ", "UG", "AG", "AM", "BS", "BB", "BZ", "BT", "BW", "BF", "CV", "CW", "DM", "FJ", "GM", "GE", "GD", "GW", "GY", "HT", "JM", "KI", "LS", "LR", "MW", "MV", "ML", "MH", "FM", "NA", "NR", "NE", "PW", "PG", "WS", "SM", "ST", "SN", "SC", "SL", "SB", "KN", "LC", "VC", "SR", "TL", "TO", "TT", "TV", "VU", "AZ", "BN", "BI", "KH", "CM", "TD", "KM", "GQ", "SZ", "GA", "GN", "KG", "LA", "MO", "MR", "MN", "NP", "RW", "TG", "UZ", "ZW", "BJ", "MG", "MU", "MZ", "AO", "CI", "DJ", "ZM", "CD", "CG", "IQ", "LY", "TJ", "VE", "ET", "XK"], "disc_number": 1, "duration_ms": 295786, "explicit": true, "external_urls": {"spotify": "https://open.spotify.com/track/25oJjxP1cVjghqjfwEVPG6"}, "href": "https://api.spotify.com/v1/tracks/25oJjxP1cVjghqjfwEVPG6", "id": "25oJjxP1cVjghqjfwEVPG6", "is_local": false, "name": "venus fly trap", "preview_url": "https://p.scdn.co/mp3-preview/0e5c26e541d6a51689dc64d75d5107a00e4d1b90?cid=2a85e163bc1d4deeb6569f6e2aff09cf", "track_number": 3, "type": "track", "uri": "spotify:track:25oJjxP1cVjghqjfwEVPG6"}, {"artists": [{"external_urls": {"spotify": "https://open.spotify.com/artist/4kqFrZkeqDfOIEqTWqbOOV"}, "href": "https://api.spotify.com/v1/artists/4kqFrZkeqDfOIEqTWqbOOV", "id": "4kqFrZkeqDfOIEqTWqbOOV", "name": "brakence", "type": "artist", "uri": "spotify:artist:4kqFrZkeqDfOIEqTWqbOOV"}], "available_markets": ["AR", "AU", "AT", "BE", "BO", "BR", "BG", "CA", "CL", "CO", "CR", "CY", "CZ", "DK", "DO", "DE", "EC", "EE", "SV", "FI", "FR", "GR", "GT", "HN", "HK", "HU", "IS", "IE", "IT", "LV", "LT", "LU", "MY", "MT", "MX", "NL", "NZ", "NI", "NO", "PA", "PY", "PE", "PH", "PL", "PT", "SG", "SK", "ES", "SE", "CH", "TW", "TR", "UY", "US", "GB", "AD", "LI", "MC", "ID", "JP", "TH", "VN", "RO", "IL", "ZA", "SA", "AE", "BH", "QA", "OM", "KW", "EG", "MA", "DZ", "TN", "LB", "JO", "PS", "IN", "BY", "KZ", "MD", "UA", "AL", "BA", "HR", "ME", "MK", "RS", "SI", "KR", "BD", "PK", "LK", "GH", "KE", "NG", "TZ", "UG", "AG", "AM", "BS", "BB", "BZ", "BT", "BW", "BF", "CV", "CW", "DM", "FJ", "GM", "GE", "GD", "GW", "GY", "HT", "JM", "KI", "LS", "LR", "MW", "MV", "ML", "MH", "FM", "NA", "NR", "NE", "PW", "PG", "WS", "SM", "ST", "SN", "SC", "SL", "SB", "KN", "LC", "VC", "SR", "TL", "TO", "TT", "TV", "VU", "AZ", "BN", "BI", "KH", "CM", "TD", "KM", "GQ", "SZ", "GA", "GN", "KG", "LA", "MO", "MR", "MN", "NP", "RW", "TG", "UZ", "ZW", "BJ", "MG", "MU", "MZ", "AO", "CI", "DJ", "ZM", "CD", "CG", "IQ", "LY", "TJ", "VE", "ET", "XK"], "disc_number": 1, "duration_ms": 272240, "explicit": true, "external_urls": {"spotify": "https://open.spotify.com/track/7q0nYf8OYd9TXeA4LTY4nZ"}, "href": "https://api.spotify.com/v1/tracks/7q0nYf8OYd9TXeA4LTY4nZ", "id": "7q0nYf8OYd9TXeA4LTY4nZ", "is_local": false, "name": "teeth", "preview_url": "https://p.scdn.co/mp3-preview/19502b3cb0f615cd9a708299bdc11cf15a2231da?cid=2a85e163bc1d4deeb6569f6e2aff09cf", "track_number": 4, "type": "track", "uri": "spotify:track:7q0nYf8OYd9TXeA4LTY4nZ"}, {"artists": [{"external_urls": {"spotify": "https://open.spotify.com/artist/4kqFrZkeqDfOIEqTWqbOOV"}, "href": "https://api.spotify.com/v1/artists/4kqFrZkeqDfOIEqTWqbOOV", "id": "4kqFrZkeqDfOIEqTWqbOOV", "name": "brakence", "type": "artist", "uri": "spotify:artist:4kqFrZkeqDfOIEqTWqbOOV"}], "available_markets": ["AR", "AU", "AT", "BE", "BO", "BR", "BG", "CA", "CL", "CO", "CR", "CY", "CZ", "DK", "DO", "DE", "EC", "EE", "SV", "FI", "FR", "GR", "GT", "HN", "HK", "HU", "IS", "IE", "IT", "LV", "LT", "LU", "MY", "MT", "MX", "NL", "NZ", "NI", "NO", "PA", "PY", "PE", "PH", "PL", "PT", "SG", "SK", "ES", "SE", "CH", "TW", "TR", "UY", "US", "GB", "AD", "LI", "MC", "ID", "JP", "TH", "VN", "RO", "IL", "ZA", "SA", "AE", "BH", "QA", "OM", "KW", "EG", "MA", "DZ", "TN", "LB", "JO", "PS", "IN", "BY", "KZ", "MD", "UA", "AL", "BA", "HR", "ME", "MK", "RS", "SI", "KR", "BD", "PK", "LK", "GH", "KE", "NG", "TZ", "UG", "AG", "AM", "BS", "BB", "BZ", "BT", "BW", "BF", "CV", "CW", "DM", "FJ", "GM", "GE", "GD", "GW", "GY", "HT", "JM", "KI", "LS", "LR", "MW", "MV", "ML", "MH", "FM", "NA", "NR", "NE", "PW", "PG", "WS", "SM", "ST", "SN", "SC", "SL", "SB", "KN", "LC", "VC", "SR", "TL", "TO", "TT", "TV", "VU", "AZ", "BN", "BI", "KH", "CM", "TD", "KM", "GQ", "SZ", "GA", "GN", "KG", "LA", "MO", "MR", "MN", "NP", "RW", "TG", "UZ", "ZW", "BJ", "MG", "MU", "MZ", "AO", "CI", "DJ", "ZM", "CD", "CG", "IQ", "LY", "TJ", "VE", "ET", "XK"], "disc_number": 1, "duration_ms": 209973, "explicit": true, "external_urls": {"spotify": "https://open.spotify.com/track/1o0hKMX2d4wIViz31dR7sG"}, "href": "https://api.spotify.com/v1/tracks/1o0hKMX2d4wIViz31dR7sG", "id": "1o0hKMX2d4wIViz31dR7sG", "is_local": false, "name": "intellectual greed", "preview_url": "https://p.scdn.co/mp3-preview/70a866463734ce51d6d7c8560d33f07d19f84a76?cid=2a85e163bc1d4deeb6569f6e2aff09cf", "track_number": 5, "type": "track", "uri": "spotify:track:1o0hKMX2d4wIViz31dR7sG"}, {"artists": [{"external_urls": {"spotify": "https://open.spotify.com/artist/4kqFrZkeqDfOIEqTWqbOOV"}, "href": "https://api.spotify.com/v1/artists/4kqFrZkeqDfOIEqTWqbOOV", "id": "4kqFrZkeqDfOIEqTWqbOOV", "name": "brakence", "type": "artist", "uri": "spotify:artist:4kqFrZkeqDfOIEqTWqbOOV"}], "available_markets": ["AR", "AU", "AT", "BE", "BO", "BR", "BG", "CA", "CL", "CO", "CR", "CY", "CZ", "DK", "DO", "DE", "EC", "EE", "SV", "FI", "FR", "GR", "GT", "HN", "HK", "HU", "IS", "IE", "IT", "LV", "LT", "LU", "MY", "MT", "MX", "NL", "NZ", "NI", "NO", "PA", "PY", "PE", "PH", "PL", "PT", "SG", "SK", "ES", "SE", "CH", "TW", "TR", "UY", "US", "GB", "AD", "LI", "MC", "ID", "JP", "TH", "VN", "RO", "IL", "ZA", "SA", "AE", "BH", "QA", "OM", "KW", "EG", "MA", "DZ", "TN", "LB", "JO", "PS", "IN", "BY", "KZ", "MD", "UA", "AL", "BA", "HR", "ME", "MK", "RS", "SI", "KR", "BD", "PK", "LK", "GH", "KE", "NG", "TZ", "UG", "AG", "AM", "BS", "BB", "BZ", "BT", "BW", "BF", "CV", "CW", "DM", "FJ", "GM", "GE", "GD", "GW", "GY", "HT", "JM", "KI", "LS", "LR", "MW", "MV", "ML", "MH", "FM", "NA", "NR", "NE", "PW", "PG", "WS", "SM", "ST", "SN", "SC", "SL", "SB", "KN", "LC", "VC", "SR", "TL", "TO", "TT", "TV", "VU", "AZ", "BN", "BI", "KH", "CM", "TD", "KM", "GQ", "SZ", "GA", "GN", "KG", "LA", "MO", "MR", "MN", "NP", "RW", "TG", "UZ", "ZW", "BJ", "MG", "MU", "MZ", "AO", "CI", "DJ", "ZM", "CD", "CG", "IQ", "LY", "TJ", "VE", "ET", "XK"], "disc_number": 1, "duration_ms": 209706, "explicit": true, "external_urls": {"spotify": "https://open.spotify.com/track/61Ph6Q4HYgWUVGulPszt9n"}, "href": "https://api.spotify.com/v1/tracks/61Ph6Q4HYgWUVGulPszt9n", "id": "61Ph6Q4HYgWUVGulPszt9n", "is_local": false, "name": "5g", "preview_url": "https://p.scdn.co/mp3-preview/c1a7c42c4b13aa31024014915c3ba76273532104?cid=2a85e163bc1d4deeb6569f6e2aff09cf", "track_number": 6, "type": "track", "uri": "spotify:track:61Ph6Q4HYgWUVGulPszt9n"}, {"artists": [{"external_urls": {"spotify": "https://open.spotify.com/artist/4kqFrZkeqDfOIEqTWqbOOV"}, "href": "https://api.spotify.com/v1/artists/4kqFrZkeqDfOIEqTWqbOOV", "id": "4kqFrZkeqDfOIEqTWqbOOV", "name": "brakence", "type": "artist", "uri": "spotify:artist:4kqFrZkeqDfOIEqTWqbOOV"}], "available_markets": ["AR", "AU", "AT", "BE", "BO", "BR", "BG", "CA", "CL", "CO", "CR", "CY", "CZ", "DK", "DO", "DE", "EC", "EE", "SV", "FI", "FR", "GR", "GT", "HN", "HK", "HU", "IS", "IE", "IT", "LV", "LT", "LU", "MY", "MT", "MX", "NL", "NZ", "NI", "NO", "PA", "PY", "PE", "PH", "PL", "PT", "SG", "SK", "ES", "SE", "CH", "TW", "TR", "UY", "US", "GB", "AD", "LI", "MC", "ID", "JP", "TH", "VN", "RO", "IL", "ZA", "SA", "AE", "BH", "QA", "OM", "KW", "EG", "MA", "DZ", "TN", "LB", "JO", "PS", "IN", "BY", "KZ", "MD", "UA", "AL", "BA", "HR", "ME", "MK", "RS", "SI", "KR", "BD", "PK", "LK", "GH", "KE", "NG", "TZ", "UG", "AG", "AM", "BS", "BB", "BZ", "BT", "BW", "BF", "CV", "CW", "DM", "FJ", "GM", "GE", "GD", "GW", "GY", "HT", "JM", "KI", "LS", "LR", "MW", "MV", "ML", "MH", "FM", "NA", "NR", "NE", "PW", "PG", "WS", "SM", "ST", "SN", "SC", "SL", "SB", "KN", "LC", "VC", "SR", "TL", "TO", "TT", "TV", "VU", "AZ", "BN", "BI", "KH", "CM", "TD", "KM", "GQ", "SZ", "GA", "GN", "KG", "LA", "MO", "MR", "MN", "NP", "RW", "TG", "UZ", "ZW", "BJ", "MG", "MU", "MZ", "AO", "CI", "DJ", "ZM", "CD", "CG", "IQ", "LY", "TJ", "VE", "ET", "XK"], "disc_number": 1, "duration_ms": 222493, "explicit": true, "external_urls": {"spotify": "https://open.spotify.com/track/3P4qX48fiwsQXEBhOgvRt0"}, "href": "https://api.spotify.com/v1/tracks/3P4qX48fiwsQXEBhOgvRt0", "id": "3P4qX48fiwsQXEBhOgvRt0", "is_local": false, "name": "preparation exercise no. 7 (trembling)", "preview_url": "https://p.scdn.co/mp3-preview/2952967dba7837aaf5e2437ca7cc13db0443c464?cid=2a85e163bc1d4deeb6569f6e2aff09cf", "track_number": 7, "type": "track", "uri": "spotify:track:3P4qX48fiwsQXEBhOgvRt0"}, {"artists": [{"external_urls": {"spotify": "https://open.spotify.com/artist/4kqFrZkeqDfOIEqTWqbOOV"}, "href": "https://api.spotify.com/v1/artists/4kqFrZkeqDfOIEqTWqbOOV", "id": "4kqFrZkeqDfOIEqTWqbOOV", "name": "brakence", "type": "artist", "uri": "spotify:artist:4kqFrZkeqDfOIEqTWqbOOV"}], "available_markets": ["AR", "AU", "AT", "BE", "BO", "BR", "BG", "CA", "CL", "CO", "CR", "CY", "CZ", "DK", "DO", "DE", "EC", "EE", "SV", "FI", "FR", "GR", "GT", "HN", "HK", "HU", "IS", "IE", "IT", "LV", "LT", "LU", "MY", "MT", "MX", "NL", "NZ", "NI", "NO", "PA", "PY", "PE", "PH", "PL", "PT", "SG", "SK", "ES", "SE", "CH", "TW", "TR", "UY", "US", "GB", "AD", "LI", "MC", "ID", "JP", "TH", "VN", "RO", "IL", "ZA", "SA", "AE", "BH", "QA", "OM", "KW", "EG", "MA", "DZ", "TN", "LB", "JO", "PS", "IN", "BY", "KZ", "MD", "UA", "AL", "BA", "HR", "ME", "MK", "RS", "SI", "KR", "BD", "PK", "LK", "GH", "KE", "NG", "TZ", "UG", "AG", "AM", "BS", "BB", "BZ", "BT", "BW", "BF", "CV", "CW", "DM", "FJ", "GM", "GE", "GD", "GW", "GY", "HT", "JM", "KI", "LS", "LR", "MW", "MV", "ML", "MH", "FM", "NA", "NR", "NE", "PW", "PG", "WS", "SM", "ST", "SN", "SC", "SL", "SB", "KN", "LC", "VC", "SR", "TL", "TO", "TT", "TV", "VU", "AZ", "BN", "BI", "KH", "CM", "TD", "KM", "GQ", "SZ", "GA", "GN", "KG", "LA", "MO", "MR", "MN", "NP", "RW", "TG", "UZ", "ZW", "BJ", "MG", "MU", "MZ", "AO", "CI", "DJ", "ZM", "CD", "CG", "IQ", "LY", "TJ", "VE", "ET", "XK"], "disc_number": 1, "duration_ms": 159346, "explicit": true, "external_urls": {"spotify": "https://open.spotify.com/track/718Z7VJDi0YRr7vXrdB0Uv"}, "href": "https://api.spotify.com/v1/tracks/718Z7VJDi0YRr7vXrdB0Uv", "id": "718Z7VJDi0YRr7vXrdB0Uv", "is_local": false, "name": "cbd", "preview_url": "https://p.scdn.co/mp3-preview/6a1d48343a1ae1d5dbf08d4ebda4b4472cd653d9?cid=2a85e163bc1d4deeb6569f6e2aff09cf", "track_number": 8, "type": "track", "uri": "spotify:track:718Z7VJDi0YRr7vXrdB0Uv"}, {"artists": [{"external_urls": {"spotify": "https://open.spotify.com/artist/4kqFrZkeqDfOIEqTWqbOOV"}, "href": "https://api.spotify.com/v1/artists/4kqFrZkeqDfOIEqTWqbOOV", "id": "4kqFrZkeqDfOIEqTWqbOOV", "name": "brakence", "type": "artist", "uri": "spotify:artist:4kqFrZkeqDfOIEqTWqbOOV"}], "available_markets": ["AR", "AU", "AT", "BE", "BO", "BR", "BG", "CA", "CL", "CO", "CR", "CY", "CZ", "DK", "DO", "DE", "EC", "EE", "SV", "FI", "FR", "GR", "GT", "HN", "HK", "HU", "IS", "IE", "IT", "LV", "LT", "LU", "MY", "MT", "MX", "NL", "NZ", "NI", "NO", "PA", "PY", "PE", "PH", "PL", "PT", "SG", "SK", "ES", "SE", "CH", "TW", "TR", "UY", "US", "GB", "AD", "LI", "MC", "ID", "JP", "TH", "VN", "RO", "IL", "ZA", "SA", "AE", "BH", "QA", "OM", "KW", "EG", "MA", "DZ", "TN", "LB", "JO", "PS", "IN", "BY", "KZ", "MD", "UA", "AL", "BA", "HR", "ME", "MK", "RS", "SI", "KR", "BD", "PK", "LK", "GH", "KE", "NG", "TZ", "UG", "AG", "AM", "BS", "BB", "BZ", "BT", "BW", "BF", "CV", "CW", "DM", "FJ", "GM", "GE", "GD", "GW", "GY", "HT", "JM", "KI", "LS", "LR", "MW", "MV", "ML", "MH", "FM", "NA", "NR", "NE", "PW", "PG", "WS", "SM", "ST", "SN", "SC", "SL", "SB", "KN", "LC", "VC", "SR", "TL", "TO", "TT", "TV", "VU", "AZ", "BN", "BI", "KH", "CM", "TD", "KM", "GQ", "SZ", "GA", "GN", "KG", "LA", "MO", "MR", "MN", "NP", "RW", "TG", "UZ", "ZW", "BJ", "MG", "MU", "MZ", "AO", "CI", "DJ", "ZM", "CD", "CG", "IQ", "LY", "TJ", "VE", "ET", "XK"], "disc_number": 1, "duration_ms": 335440, "explicit": true, "external_urls": {"spotify": "https://open.spotify.com/track/4OqHfFBX1Pw9DjiesyQpfK"}, "href": "https://api.spotify.com/v1/tracks/4OqHfFBX1Pw9DjiesyQpfK", "id": "4OqHfFBX1Pw9DjiesyQpfK", "is_local": false, "name": "stung", "preview_url": "https://p.scdn.co/mp3-preview/23eefb59c12af81945403a25bfbfc1faae027ea9?cid=2a85e163bc1d4deeb6569f6e2aff09cf", "track_number": 9, "type": "track", "uri": "spotify:track:4OqHfFBX1Pw9DjiesyQpfK"}, {"artists": [{"external_urls": {"spotify": "https://open.spotify.com/artist/4kqFrZkeqDfOIEqTWqbOOV"}, "href": "https://api.spotify.com/v1/artists/4kqFrZkeqDfOIEqTWqbOOV", "id": "4kqFrZkeqDfOIEqTWqbOOV", "name": "brakence", "type": "artist", "uri": "spotify:artist:4kqFrZkeqDfOIEqTWqbOOV"}], "available_markets": ["AR", "AU", "AT", "BE", "BO", "BR", "BG", "CA", "CL", "CO", "CR", "CY", "CZ", "DK", "DO", "DE", "EC", "EE", "SV", "FI", "FR", "GR", "GT", "HN", "HK", "HU", "IS", "IE", "IT", "LV", "LT", "LU", "MY", "MT", "MX", "NL", "NZ", "NI", "NO", "PA", "PY", "PE", "PH", "PL", "PT", "SG", "SK", "ES", "SE", "CH", "TW", "TR", "UY", "US", "GB", "AD", "LI", "MC", "ID", "JP", "TH", "VN", "RO", "IL", "ZA", "SA", "AE", "BH", "QA", "OM", "KW", "EG", "MA", "DZ", "TN", "LB", "JO", "PS", "IN", "BY", "KZ", "MD", "UA", "AL", "BA", "HR", "ME", "MK", "RS", "SI", "KR", "BD", "PK", "LK", "GH", "KE", "NG", "TZ", "UG", "AG", "AM", "BS", "BB", "BZ", "BT", "BW", "BF", "CV", "CW", "DM", "FJ", "GM", "GE", "GD", "GW", "GY", "HT", "JM", "KI", "LS", "LR", "MW", "MV", "ML", "MH", "FM", "NA", "NR", "NE", "PW", "PG", "WS", "SM", "ST", "SN", "SC", "SL", "SB", "KN", "LC", "VC", "SR", "TL", "TO", "TT", "TV", "VU", "AZ", "BN", "BI", "KH", "CM", "TD", "KM", "GQ", "SZ", "GA", "GN", "KG", "LA", "MO", "MR", "MN", "NP", "RW", "TG", "UZ", "ZW", "BJ", "MG", "MU", "MZ", "AO", "CI", "DJ", "ZM", "CD", "CG", "IQ", "LY", "TJ", "VE", "ET", "XK"], "disc_number": 1, "duration_ms": 165186, "explicit": true, "external_urls": {"spotify": "https://open.spotify.com/track/66YGJwPx1qGxTHywsFJTXe"}, "href": "https://api.spotify.com/v1/tracks/66YGJwPx1qGxTHywsFJTXe", "id": "66YGJwPx1qGxTHywsFJTXe", "is_local": false, "name": "argyle", "preview_url": "https://p.scdn.co/mp3-preview/bf1e5d379207515904c075752598cac34e2fe4bc?cid=2a85e163bc1d4deeb6569f6e2aff09cf", "track_number": 10, "type": "track", "uri": "spotify:track:66YGJwPx1qGxTHywsFJTXe"}, {"artists": [{"external_urls": {"spotify": "https://open.spotify.com/artist/4kqFrZkeqDfOIEqTWqbOOV"}, "href": "https://api.spotify.com/v1/artists/4kqFrZkeqDfOIEqTWqbOOV", "id": "4kqFrZkeqDfOIEqTWqbOOV", "name": "brakence", "type": "artist", "uri": "spotify:artist:4kqFrZkeqDfOIEqTWqbOOV"}], "available_markets": ["AR", "AU", "AT", "BE", "BO", "BR", "BG", "CA", "CL", "CO", "CR", "CY", "CZ", "DK", "DO", "DE", "EC", "EE", "SV", "FI", "FR", "GR", "GT", "HN", "HK", "HU", "IS", "IE", "IT", "LV", "LT", "LU", "MY", "MT", "MX", "NL", "NZ", "NI", "NO", "PA", "PY", "PE", "PH", "PL", "PT", "SG", "SK", "ES", "SE", "CH", "TW", "TR", "UY", "US", "GB", "AD", "LI", "MC", "ID", "JP", "TH", "VN", "RO", "IL", "ZA", "SA", "AE", "BH", "QA", "OM", "KW", "EG", "MA", "DZ", "TN", "LB", "JO", "PS", "IN", "BY", "KZ", "MD", "UA", "AL", "BA", "HR", "ME", "MK", "RS", "SI", "KR", "BD", "PK", "LK", "GH", "KE", "NG", "TZ", "UG", "AG", "AM", "BS", "BB", "BZ", "BT", "BW", "BF", "CV", "CW", "DM", "FJ", "GM", "GE", "GD", "GW", "GY", "HT", "JM", "KI", "LS", "LR", "MW", "MV", "ML", "MH", "FM", "NA", "NR", "NE", "PW", "PG", "WS", "SM", "ST", "SN", "SC", "SL", "SB", "KN", "LC", "VC", "SR", "TL", "TO", "TT", "TV", "VU", "AZ", "BN", "BI", "KH", "CM", "TD", "KM", "GQ", "SZ", "GA", "GN", "KG", "LA", "MO", "MR", "MN", "NP", "RW", "TG", "UZ", "ZW", "BJ", "MG", "MU", "MZ", "AO", "CI", "DJ", "ZM", "CD", "CG", "IQ", "LY", "TJ", "VE", "ET", "XK"], "disc_number": 1, "duration_ms": 330640, "explicit": true, "external_urls": {"spotify": "https://open.spotify.com/track/2iS3P95EkgyRAHx2hLy0ga"}, "href": "https://api.spotify.com/v1/tracks/2iS3P95EkgyRAHx2hLy0ga", "id": "2iS3P95EkgyRAHx2hLy0ga", "is_local": false, "name": "deepfake", "preview_url": "https://p.scdn.co/mp3-preview/f23b8ed9b2d825427ba56c17cf959a60474b3c30?cid=2a85e163bc1d4deeb6569f6e2aff09cf", "track_number": 11, "type": "track", "uri": "spotify:track:2iS3P95EkgyRAHx2hLy0ga"}, {"artists": [{"external_urls": {"spotify": "https://open.spotify.com/artist/4kqFrZkeqDfOIEqTWqbOOV"}, "href": "https://api.spotify.com/v1/artists/4kqFrZkeqDfOIEqTWqbOOV", "id": "4kqFrZkeqDfOIEqTWqbOOV", "name": "brakence", "type": "artist", "uri": "spotify:artist:4kqFrZkeqDfOIEqTWqbOOV"}], "available_markets": ["AR", "AU", "AT", "BE", "BO", "BR", "BG", "CA", "CL", "CO", "CR", "CY", "CZ", "DK", "DO", "DE", "EC", "EE", "SV", "FI", "FR", "GR", "GT", "HN", "HK", "HU", "IS", "IE", "IT", "LV", "LT", "LU", "MY", "MT", "MX", "NL", "NZ", "NI", "NO", "PA", "PY", "PE", "PH", "PL", "PT", "SG", "SK", "ES", "SE", "CH", "TW", "TR", "UY", "US", "GB", "AD", "LI", "MC", "ID", "JP", "TH", "VN", "RO", "IL", "ZA", "SA", "AE", "BH", "QA", "OM", "KW", "EG", "MA", "DZ", "TN", "LB", "JO", "PS", "IN", "BY", "KZ", "MD", "UA", "AL", "BA", "HR", "ME", "MK", "RS", "SI", "KR", "BD", "PK", "LK", "GH", "KE", "NG", "TZ", "UG", "AG", "AM", "BS", "BB", "BZ", "BT", "BW", "BF", "CV", "CW", "DM", "FJ", "GM", "GE", "GD", "GW", "GY", "HT", "JM", "KI", "LS", "LR", "MW", "MV", "ML", "MH", "FM", "NA", "NR", "NE", "PW", "PG", "WS", "SM", "ST", "SN", "SC", "SL", "SB", "KN", "LC", "VC", "SR", "TL", "TO", "TT", "TV", "VU", "AZ", "BN", "BI", "KH", "CM", "TD", "KM", "GQ", "SZ", "GA", "GN", "KG", "LA", "MO", "MR", "MN", "NP", "RW", "TG", "UZ", "ZW", "BJ", "MG", "MU", "MZ", "AO", "CI", "DJ", "ZM", "CD", "CG", "IQ", "LY", "TJ", "VE", "ET", "XK"], "disc_number": 1, "duration_ms": 374546, "explicit": true, "external_urls": {"spotify": "https://open.spotify.com/track/0uOgY7Q90XkqibGImcnAER"}, "href": "https://api.spotify.com/v1/tracks/0uOgY7Q90XkqibGImcnAER", "id": "0uOgY7Q90XkqibGImcnAER", "is_local": false, "name": "introvert", "preview_url": "https://p.scdn.co/mp3-preview/2f891a1244791c319bdfcc8981b890d520991353?cid=2a85e163bc1d4deeb6569f6e2aff09cf", "track_number": 12, "type": "track", "uri": "spotify:track:0uOgY7Q90XkqibGImcnAER"}, {"artists": [{"external_urls": {"spotify": "https://open.spotify.com/artist/4kqFrZkeqDfOIEqTWqbOOV"}, "href": "https://api.spotify.com/v1/artists/4kqFrZkeqDfOIEqTWqbOOV", "id": "4kqFrZkeqDfOIEqTWqbOOV", "name": "brakence", "type": "artist", "uri": "spotify:artist:4kqFrZkeqDfOIEqTWqbOOV"}], "available_markets": ["AR", "AU", "AT", "BE", "BO", "BR", "BG", "CA", "CL", "CO", "CR", "CY", "CZ", "DK", "DO", "DE", "EC", "EE", "SV", "FI", "FR", "GR", "GT", "HN", "HK", "HU", "IS", "IE", "IT", "LV", "LT", "LU", "MY", "MT", "MX", "NL", "NZ", "NI", "NO", "PA", "PY", "PE", "PH", "PL", "PT", "SG", "SK", "ES", "SE", "CH", "TW", "TR", "UY", "US", "GB", "AD", "LI", "MC", "ID", "JP", "TH", "VN", "RO", "IL", "ZA", "SA", "AE", "BH", "QA", "OM", "KW", "EG", "MA", "DZ", "TN", "LB", "JO", "PS", "IN", "BY", "KZ", "MD", "UA", "AL", "BA", "HR", "ME", "MK", "RS", "SI", "KR", "BD", "PK", "LK", "GH", "KE", "NG", "TZ", "UG", "AG", "AM", "BS", "BB", "BZ", "BT", "BW", "BF", "CV", "CW", "DM", "FJ", "GM", "GE", "GD", "GW", "GY", "HT", "JM", "KI", "LS", "LR", "MW", "MV", "ML", "MH", "FM", "NA", "NR", "NE", "PW", "PG", "WS", "SM", "ST", "SN", "SC", "SL", "SB", "KN", "LC", "VC", "SR", "TL", "TO", "TT", "TV", "VU", "AZ", "BN", "BI", "KH", "CM", "TD", "KM", "GQ", "SZ", "GA", "GN", "KG", "LA", "MO", "MR", "MN", "NP", "RW", "TG", "UZ", "ZW", "BJ", "MG", "MU", "MZ", "AO", "CI", "DJ", "ZM", "CD", "CG", "IQ", "LY", "TJ", "VE", "ET", "XK"], "disc_number": 1, "duration_ms": 162906, "explicit": true, "external_urls": {"spotify": "https://open.spotify.com/track/0tocRPyNlOEk74o27EYGFe"}, "href": "https://api.spotify.com/v1/tracks/0tocRPyNlOEk74o27EYGFe", "id": "0tocRPyNlOEk74o27EYGFe", "is_local": false, "name": "hypochondriac", "preview_url": "https://p.scdn.co/mp3-preview/cb1f16397d9f3c73df809dc3388762dd085c85fa?cid=2a85e163bc1d4deeb6569f6e2aff09cf", "track_number": 13, "type": "track", "uri": "spotify:track:0tocRPyNlOEk74o27EYGFe"}]