{"tracks": [{"name": "Cops and robbers", "id": "08AznbP5RLxjaFOZTqOI9w", "audio_features": {"danceability": 0.296, "energy": 0.643, "key": 8, "loudness": -4.758, "mode": 1, "speechiness": 0.135, "acousticness": 0.0236, "instrumentalness": 0, "liveness": 0.329, "valence": 0.429, "tempo": 169.681, "type": "audio_features", "id": "08AznbP5RLxjaFOZTqOI9w", "uri": "spotify:track:08AznbP5RLxjaFOZTqOI9w", "track_href": "https://api.spotify.com/v1/tracks/08AznbP5RLxjaFOZTqOI9w", "analysis_url": "https://api.spotify.com/v1/audio-analysis/08AznbP5RLxjaFOZTqOI9w", "duration_ms": 265960, "time_signature": 4}}, {"name": "Locals (Girls like us) [with gabby start]", "id": "0MK6lVnmhVulpP62vkZBWV", "audio_features": {"danceability": 0.722, "energy": 0.683, "key": 9, "loudness": -5.538, "mode": 1, "speechiness": 0.175, "acousticness": 0.0113, "instrumentalness": 0, "liveness": 0.0942, "valence": 0.514, "tempo": 133.966, "type": "audio_features", "id": "0MK6lVnmhVulpP62vkZBWV", "uri": "spotify:track:0MK6lVnmhVulpP62vkZBWV", "track_href": "https://api.spotify.com/v1/tracks/0MK6lVnmhVulpP62vkZBWV", "analysis_url": "https://api.spotify.com/v1/audio-analysis/0MK6lVnmhVulpP62vkZBWV", "duration_ms": 258085, "time_signature": 4}}, {"name": "Duhhhhhhhhhhhhhhhhh", "id": "1SHOlAdcna7plmlXYRWWEu", "audio_features": {"danceability": 0.598, "energy": 0.397, "key": 8, "loudness": -7.748, "mode": 0, "speechiness": 0.0516, "acousticness": 0.538, "instrumentalness": 0, "liveness": 0.0876, "valence": 0.294, "tempo": 76.106, "type": "audio_features", "id": "1SHOlAdcna7plmlXYRWWEu", "uri": "spotify:track:1SHOlAdcna7plmlXYRWWEu", "track_href": "https://api.spotify.com/v1/tracks/1SHOlAdcna7plmlXYRWWEu", "analysis_url": "https://api.spotify.com/v1/audio-analysis/1SHOlAdcna7plmlXYRWWEu", "duration_ms": 247796, "time_signature": 3}}, {"name": "You don't even know who I am", "id": "195AO4g5cBQScmtDWNdm1C", "audio_features": {"danceability": 0.563, "energy": 0.16, "key": 9, "loudness": -12.734, "mode": 1, "speechiness": 0.186, "acousticness": 0.859, "instrumentalness": 0.00322, "liveness": 0.268, "valence": 0.307, "tempo": 75.017, "type": "audio_features", "id": "195AO4g5cBQScmtDWNdm1C", "uri": "spotify:track:195AO4g5cBQScmtDWNdm1C", "track_href": "https://api.spotify.com/v1/tracks/195AO4g5cBQScmtDWNdm1C", "analysis_url": "https://api.spotify.com/v1/audio-analysis/195AO4g5cBQScmtDWNdm1C", "duration_ms": 244023, "time_signature": 3}}, {"name": "Johnny johnny johnny", "id": "60qaApzoNFsAXhhPc5zDxh", "audio_features": {"danceability": 0.716, "energy": 0.716, "key": 0, "loudness": -5.293, "mode": 1, "speechiness": 0.181, "acousticness": 0.051, "instrumentalness": 0, "liveness": 0.162, "valence": 0.857, "tempo": 131.98, "type": "audio_features", "id": "60qaApzoNFsAXhhPc5zDxh", "uri": "spotify:track:60qaApzoNFsAXhhPc5zDxh", "track_href": "https://api.spotify.com/v1/tracks/60qaApzoNFsAXhhPc5zDxh", "analysis_url": "https://api.spotify.com/v1/audio-analysis/60qaApzoNFsAXhhPc5zDxh", "duration_ms": 245123, "time_signature": 4}}, {"name": "Shoot to kill, kill your darlings", "id": "49jZ7brj34fVrIdDBfRAMp", "audio_features": {"danceability": 0.57, "energy": 0.691, "key": 7, "loudness": -6.727, "mode": 1, "speechiness": 0.321, "acousticness": 0.0183, "instrumentalness": 0.000494, "liveness": 0.306, "valence": 0.185, "tempo": 167.833, "type": "audio_features", "id": "49jZ7brj34fVrIdDBfRAMp", "uri": "spotify:track:49jZ7brj34fVrIdDBfRAMp", "track_href": "https://api.spotify.com/v1/tracks/49jZ7brj34fVrIdDBfRAMp", "analysis_url": "https://api.spotify.com/v1/audio-analysis/49jZ7brj34fVrIdDBfRAMp", "duration_ms": 304411, "time_signature": 4}}, {"name": "Horror movie soundtrack", "id": "0Cx0rSjGfg5nQ81YWp4ywH", "audio_features": {"danceability": 0.242, "energy": 0.15, "key": 4, "loudness": -17.009, "mode": 0, "speechiness": 0.0648, "acousticness": 0.702, "instrumentalness": 0.000249, "liveness": 0.0996, "valence": 0.0405, "tempo": 76.931, "type": "audio_features", "id": "0Cx0rSjGfg5nQ81YWp4ywH", "uri": "spotify:track:0Cx0rSjGfg5nQ81YWp4ywH", "track_href": "https://api.spotify.com/v1/tracks/0Cx0rSjGfg5nQ81YWp4ywH", "analysis_url": "https://api.spotify.com/v1/audio-analysis/0Cx0rSjGfg5nQ81YWp4ywH", "duration_ms": 232435, "time_signature": 4}}, {"name": "Old money bitch", "id": "69G9nIj6Pb1HfqFXa9DGFs", "audio_features": {"danceability": 0.727, "energy": 0.7, "key": 11, "loudness": -5.427, "mode": 0, "speechiness": 0.0981, "acousticness": 0.034, "instrumentalness": 0, "liveness": 0.102, "valence": 0.875, "tempo": 139.991, "type": "audio_features", "id": "69G9nIj6Pb1HfqFXa9DGFs", "uri": "spotify:track:69G9nIj6Pb1HfqFXa9DGFs", "track_href": "https://api.spotify.com/v1/tracks/69G9nIj6Pb1HfqFXa9DGFs", "analysis_url": "https://api.spotify.com/v1/audio-analysis/69G9nIj6Pb1HfqFXa9DGFs", "duration_ms": 245858, "time_signature": 4}}, {"name": "Geez louise (with henhouse!)", "id": "3v1awewJB3C5QAC8hgggHK", "audio_features": {"danceability": 0.363, "energy": 0.884, "key": 0, "loudness": -5.052, "mode": 1, "speechiness": 0.0922, "acousticness": 0.383, "instrumentalness": 3.45e-06, "liveness": 0.0847, "valence": 0.303, "tempo": 101.995, "type": "audio_features", "id": "3v1awewJB3C5QAC8hgggHK", "uri": "spotify:track:3v1awewJB3C5QAC8hgggHK", "track_href": "https://api.spotify.com/v1/tracks/3v1awewJB3C5QAC8hgggHK", "analysis_url": "https://api.spotify.com/v1/audio-analysis/3v1awewJB3C5QAC8hgggHK", "duration_ms": 440904, "time_signature": 4}}, {"name": "Seventyseven dog years", "id": "3irkFAVOrI6hy6PB0C725w", "audio_features": {"danceability": 0.499, "energy": 0.376, "key": 7, "loudness": -8.599, "mode": 1, "speechiness": 0.034, "acousticness": 0.573, "instrumentalness": 0.000574, "liveness": 0.0999, "valence": 0.346, "tempo": 98.498, "type": "audio_features", "id": "3irkFAVOrI6hy6PB0C725w", "uri": "spotify:track:3irkFAVOrI6hy6PB0C725w", "track_href": "https://api.spotify.com/v1/tracks/3irkFAVOrI6hy6PB0C725w", "analysis_url": "https://api.spotify.com/v1/audio-analysis/3irkFAVOrI6hy6PB0C725w", "duration_ms": 275127, "time_signature": 4}}, {"name": "Uncanny long arms (with Jane Remover)", "id": "3j38fb5Pna0iFQhtUGuT8c", "audio_features": {"danceability": 0.4, "energy": 0.456, "key": 11, "loudness": -9.088, "mode": 1, "speechiness": 0.0455, "acousticness": 0.355, "instrumentalness": 6.03e-05, "liveness": 0.109, "valence": 0.237, "tempo": 88.121, "type": "audio_features", "id": "3j38fb5Pna0iFQhtUGuT8c", "uri": "spotify:track:3j38fb5Pna0iFQhtUGuT8c", "track_href": "https://api.spotify.com/v1/tracks/3j38fb5Pna0iFQhtUGuT8c", "analysis_url": "https://api.spotify.com/v1/audio-analysis/3j38fb5Pna0iFQhtUGuT8c", "duration_ms": 326531, "time_signature": 4}}, {"name": "Good luck final girl", "id": "5ff5T1YyjZJz8eoM6HFl95", "audio_features": {"danceability": 0.51, "energy": 0.322, "key": 9, "loudness": -11.48, "mode": 1, "speechiness": 0.0428, "acousticness": 0.594, "instrumentalness": 4.84e-06, "liveness": 0.0965, "valence": 0.525, "tempo": 79.885, "type": "audio_features", "id": "5ff5T1YyjZJz8eoM6HFl95", "uri": "spotify:track:5ff5T1YyjZJz8eoM6HFl95", "track_href": "https://api.spotify.com/v1/tracks/5ff5T1YyjZJz8eoM6HFl95", "analysis_url": "https://api.spotify.com/v1/audio-analysis/5ff5T1YyjZJz8eoM6HFl95", "duration_ms": 208749, "time_signature": 4}}], "artist_info": {"popularity": 49, "followers": 71824, "genres": ["hyperpop"], "images": [{"height": 640, "url": "https://i.scdn.co/image/ab6761610000e5ebde8dfaf8e64fee65ef479e68", "width": 640}, {"height": 320, "url": "https://i.scdn.co/image/ab67616100005174de8dfaf8e64fee65ef479e68", "width": 320}, {"height": 160, "url": "https://i.scdn.co/image/ab6761610000f178de8dfaf8e64fee65ef479e68", "width": 160}], "external_urls": {"spotify": "https://open.spotify.com/artist/7HfUJxeVTgrvhk0eWHFzV7"}, "spotify_uri": "spotify:artist:7HfUJxeVTgrvhk0eWHFzV7", "spotify_url": "https://open.spotify.com/artist/7HfUJxeVTgrvhk0eWHFzV7"}}